phewgle/__init__.py
phewgle/common.py
phewgle/fugle.py
phewgle-0.1.4.dist-info/METADATA
phewgle-0.1.4.dist-info/WHEEL
phewgle-0.1.4.dist-info/RECORD
